hg/__init__.py
hg/datasets/__init__.py
hg/datasets/dataset_info.yaml
hg/datasets/amazon/__init__.py
hg/datasets/amazon/amazon.py
hg/datasets/grand/__init__.py
hg/datasets/grand/grand.py
hg/datasets/hg_formatter/HybridGraphFormatter.py
hg/datasets/hg_formatter/__init__.py
hg/datasets/hg_samplers/__init__.py
hg/datasets/hg_samplers/graph_saint.py
hg/datasets/hg_samplers/random_sampler.py
hg/datasets/hg_spliter/__init__.py
hg/datasets/hg_spliter/spliter.py
hg/datasets/musae/__init__.py
hg/datasets/musae/facebook.py
hg/datasets/musae/github.py
hg/datasets/musae/twitch.py
hg/datasets/musae/wikipedia.py
hg/datasets/standard/GraphStats.py
hg/datasets/standard/__init__.py
hg/datasets/standard/benchmark.py
hg/hybrid_graph/__init__.py
hg/hybrid_graph/cli.py
hg/hybrid_graph/io/__init__.py
hg/hybrid_graph/io/factory.py
hg/hybrid_graph/io/utils.py
hg/hybrid_graph/models/__init__.py
hg/hybrid_graph/models/ensemble/__init__.py
hg/hybrid_graph/models/ensemble/average_prediction.py
hg/hybrid_graph/models/gnn/__init__.py
hg/hybrid_graph/models/gnn/baseline.py
hg/hybrid_graph/models/gnn/gat.py
hg/hybrid_graph/models/gnn/hyper.py
hg/hybrid_graph/models/gnn/linearprobe.py
hg/hybrid_graph/sessions/__init__.py
hg/hybrid_graph/sessions/plt_wrapper.py
hg/hybrid_graph/sessions/test.py
hg/hybrid_graph/sessions/train.py
hybrid_graph-0.61.dist-info/LICENSE
hybrid_graph-0.61.dist-info/METADATA
hybrid_graph-0.61.dist-info/WHEEL
hybrid_graph-0.61.dist-info/entry_points.txt
hybrid_graph-0.61.dist-info/top_level.txt
hybrid_graph-0.61.dist-info/RECORD
