Metadata-Version: 2.1
Name: hybrid-graph
Version: 0.61
Summary: A python package for accessing and Hybrid-graph Datasets and train-eval framework for GNNs
Home-page: https://github.com/Zehui127/hybrid-graph-benchmark/
Author: Xiangyu Zhao;Zehui Li
Author-email: zehui.li22@imperial.ac.uk, x.zhao22@imperial.ac.uk
Classifier: Programming Language :: Python :: 3
Classifier: License :: OSI Approved :: MIT License
Classifier: Operating System :: OS Independent
License-File: LICENSE
Requires-Dist: torch
Requires-Dist: torch-scatter
Requires-Dist: torch-sparse
Requires-Dist: torch-geometric (==2.2.0)
Requires-Dist: ipdb (==0.13.13)
Requires-Dist: ipython (==8.13.2)
Requires-Dist: matplotlib (==3.7.1)
Requires-Dist: networkx (==3.1)
Requires-Dist: numpy (==1.24.2)
Requires-Dist: pytorch-lightning (==1.9.3)
Requires-Dist: PyYAML (==6.0)
Requires-Dist: scikit-learn (==1.2.1)
Requires-Dist: seaborn (==0.12.2)
Requires-Dist: torchmetrics (==0.11.1)
